azkaban_ctrl/__init__.py
azkaban_ctrl/greet.py
azkaban_ctrl-0.3.1.dist-info/METADATA
azkaban_ctrl-0.3.1.dist-info/WHEEL
azkaban_ctrl-0.3.1.dist-info/top_level.txt
azkaban_ctrl-0.3.1.dist-info/RECORD
