Metadata-Version: 2.1
Name: azkaban-ctrl
Version: 0.3.1
Summary: A package to control Azkaban workflows.
Home-page: https://github.com/yourusername/azkaban_ctrl
Author: Your Name
Author-email: your.email@example.com
License: UNKNOWN
Platform: UNKNOWN
Classifier: Programming Language :: Python :: 3
Classifier: License :: OSI Approved :: MIT License
Classifier: Operating System :: OS Independent
Requires-Python: >=3.6
